cyber_ops/__init__.py
cyber_ops/yap.py
cyber_ops-0.1.1.dist-info/LICENSE
cyber_ops-0.1.1.dist-info/METADATA
cyber_ops-0.1.1.dist-info/WHEEL
cyber_ops-0.1.1.dist-info/top_level.txt
cyber_ops-0.1.1.dist-info/RECORD
