Metadata-Version: 2.1
Name: cyber_ops
Version: 0.1.1
Summary: Cyberops toolkit
Author: Cyber Whiz
Author-email: cyberwhizy@gmail.com
Classifier: Programming Language :: Python :: 3
Classifier: License :: OSI Approved :: MIT License
Classifier: Operating System :: OS Independent
Requires-Python: >=3.6
License-File: LICENSE
